README.rst
setup.py
octbrowser/__init__.py
octbrowser/browser.py
octbrowser/exceptions.py
octbrowser.egg-info/PKG-INFO
octbrowser.egg-info/SOURCES.txt
octbrowser.egg-info/dependency_links.txt
octbrowser.egg-info/requires.txt
octbrowser.egg-info/top_level.txt