Metadata-Version: 1.1
Name: octbrowser
Version: 0.4.1
Summary: A web scrapper based on lxml library.
Home-page: https://github.com/karec/oct-browser
Author: Emmanuel Valette
Author-email: manu.valette@gmail.com
License: UNKNOWN
Download-URL: https://github.com/karec/oct-browser/archive/master.zip
Keywords: testing,mechanize,webscrapper,browser,web,lxml,html
Platform: UNKNOWN
Classifier: Development Status :: 4 - Beta
Classifier: Environment :: Console
Classifier: Intended Audience :: Developers
Classifier: License :: OSI Approved :: MIT License
Classifier: Programming Language :: Python :: 2.7
Classifier: Programming Language :: Python :: 3.4
